axon/__init__.py
axon/session.py
axon/integrations/__init__.py
axon/integrations/django.py
axon/integrations/fast.py
axon/integrations/flask.py
cortex_axon_py-0.1.24.dist-info/METADATA
cortex_axon_py-0.1.24.dist-info/WHEEL
cortex_axon_py-0.1.24.dist-info/top_level.txt
cortex_axon_py-0.1.24.dist-info/RECORD
