Metadata-Version: 2.2
Name: cortex-axon-py
Version: 0.1.24
Summary: Flask middleware to forward inbound headers automatically
Requires-Dist: Flask>=2.0
Requires-Dist: requests>=2.0
Provides-Extra: fastapi
Requires-Dist: starlette>=0.19.1; extra == "fastapi"
